combination/__init__.py
combination/core.py
combination_py-1.0.1.dist-info/LICENSE
combination_py-1.0.1.dist-info/METADATA
combination_py-1.0.1.dist-info/WHEEL
combination_py-1.0.1.dist-info/top_level.txt
combination_py-1.0.1.dist-info/RECORD
