Metadata-Version: 2.1
Name: combination-py
Version: 1.0.1
Summary: Python package for combination calculation
Home-page: https://github.com/m-star18/combination_py
Author: Ryusei Ito
Author-email: 31807@toyota.kosen-ac.jp
License: Apache Software License 2.0
Platform: UNKNOWN
Requires-Python: >=3.6, <3.9
License-File: LICENSE
